axia/__init__.py
axia/dataset.py
axia/loader.py
axia/report.py
axia/sbg_survival.py
axia/shifted_beta_geometric.py
axia/util.py
axia-0.1.2.dist-info/LICENSE
axia-0.1.2.dist-info/METADATA
axia-0.1.2.dist-info/WHEEL
axia-0.1.2.dist-info/top_level.txt
axia-0.1.2.dist-info/RECORD
