Metadata-Version: 2.1
Name: axia
Version: 0.1.2
Summary: An alternative to survival analysis using the shifted beta-geometric model.
Author-email: Fernando Nogueira <author@example.com>
Project-URL: Homepage, https://github.com/fmfn/axia
Project-URL: Bug Tracker, https://github.com/fmfn/axia/issues
Classifier: Programming Language :: Python :: 3
Classifier: License :: OSI Approved :: MIT License
Classifier: Operating System :: OS Independent
Requires-Python: >=3.5
License-File: LICENSE
